visualife/__init__.py
visualife/calc/DataBins.py
visualife/calc/DataBins2D.py
visualife/calc/Histogram.py
visualife/calc/Histogram2D.py
visualife/calc/__init__.py
visualife/calc/math_utils.py
visualife/core/CanvasViewport.py
visualife/core/DraggablePlot.py
visualife/core/Feature2D.py
visualife/core/HtmlViewport.py
visualife/core/Plot.py
visualife/core/SvgViewport.py
visualife/core/__init__.py
visualife/core/axes.py
visualife/core/shapes.py
visualife/core/styles.py
visualife/core/three_d/MoleculePanel.py
visualife/core/three_d/Svg3DPanel.py
visualife/core/three_d/__init__.py
visualife/data/Atom.py
visualife/data/Bond.py
visualife/data/Chain.py
visualife/data/HSSP.py
visualife/data/Molecule.py
visualife/data/Residue.py
visualife/data/ScoreFile.py
visualife/data/Structure.py
visualife/data/__init__.py
visualife/data/pdb_utils.py
visualife/data/read_mol.py
visualife/data/read_pdb.py
visualife/data/read_sequences.py
visualife/diagrams/Diagram.py
visualife/diagrams/InteractiveDiagram.py
visualife/diagrams/__init__.py
visualife/serverside/__init__.py
visualife/serverside/utils.py
visualife/utils/__init__.py
visualife/utils/html_utils.py
visualife/utils/text_utils.py
visualife/widget/FileReaderWidget.py
visualife/widget/GLViewerWidget.py
visualife/widget/MSAViewer.py
visualife/widget/SecondaryStructureViewer.py
visualife/widget/SequenceFeaturesBar.py
visualife/widget/SequenceViewer.py
visualife/widget/StructureViewer.py
visualife/widget/TableWidget.py
visualife/widget/TooltipWidget.py
visualife/widget/__init__.py
visualife-0.8.dist-info/LICENSE
visualife-0.8.dist-info/METADATA
visualife-0.8.dist-info/WHEEL
visualife-0.8.dist-info/top_level.txt
visualife-0.8.dist-info/RECORD
