Metadata-Version: 2.1
Name: visualife
Version: 0.8
Summary: Interactive visualisation for the web
Home-page: https://bitbucket.org/dgront/visualife/
Author: Justyna Kryś, Dominik Gront
Author-email: dgront@chem.uw.edu.pl
License: UNKNOWN
Platform: UNKNOWN
Classifier: Programming Language :: Python :: 3
Classifier: License :: OSI Approved :: Apache Software License
Classifier: Operating System :: OS Independent
Requires-Python: >=3.6
